deleashes/__init__.py
deleashes/client.py
deleashes/logging.py
deleashes_sdk-0.1.2.dist-info/METADATA
deleashes_sdk-0.1.2.dist-info/WHEEL
deleashes_sdk-0.1.2.dist-info/top_level.txt
deleashes_sdk-0.1.2.dist-info/RECORD
