Metadata-Version: 2.4
Name: deleashes-sdk
Version: 0.1.2
Summary: SDK for Deleashes feature flag management service
Home-page: https://github.com/explrms/DeleashesSDK-python
Author: exp1rms
Author-email: imExpelliarmus@yandex.ru
Project-URL: Bug Tracker, https://github.com/explrms/DeleashesSDK-python/issues
Project-URL: Documentation, https://github.com/explrms/DeleashesSDK-python
Project-URL: Source Code, https://github.com/explrms/DeleashesSDK-python
Keywords: feature flags,feature toggles,a/b testing,release management
Classifier: Development Status :: 3 - Alpha
Classifier: Intended Audience :: Developers
Classifier: License :: OSI Approved :: MIT License
Classifier: Programming Language :: Python :: 3.8
Classifier: Programming Language :: Python :: 3.9
Classifier: Programming Language :: Python :: 3.10
Classifier: Programming Language :: Python :: 3.11
Classifier: Programming Language :: Python :: 3.12
Classifier: Programming Language :: Python :: 3.13
Classifier: Topic :: Software Development :: Libraries
Requires-Python: >=3.8
Requires-Dist: requests>=2.25.0
Dynamic: author
Dynamic: author-email
Dynamic: classifier
Dynamic: description
Dynamic: description-content-type
Dynamic: home-page
Dynamic: keywords
Dynamic: project-url
Dynamic: requires-dist
Dynamic: requires-python
Dynamic: summary
